Metadata-Version: 2.1
Name: covert
Version: 0.7.0
Summary: File and message encryption GUI and CLI
Home-page: https://github.com/covert-encryption/covert
Author: Covert Encryption
Author-email: covert-encryption@users.noreply.github.com
License: UNKNOWN
Platform: UNKNOWN
Classifier: Programming Language :: Python :: 3
Classifier: License :: OSI Approved :: MIT License
Classifier: License :: Public Domain
Classifier: Operating System :: OS Independent
Requires-Python: >=3.9
Provides-Extra: gui
Provides-Extra: test
Provides-Extra: dev
